ziphy/fastapi_utils/__init__.py
ziphy/fastapi_utils/encoding.py
ziphy/fastapi_utils/exceptions.py
ziphy/fastapi_utils/middleware.py
ziphy/fastapi_utils/py.typed
ziphy_fastapi_utils-2.0.4.dist-info/METADATA
ziphy_fastapi_utils-2.0.4.dist-info/WHEEL
ziphy_fastapi_utils-2.0.4.dist-info/RECORD
