Metadata-Version: 2.1
Name: ziphy-fastapi-utils
Version: 2.0.4
Summary: Ziphy FastAPI Utils
Author: ZiphyCare LLC
Author-email: support@ziphycare.com
Requires-Python: >=3.11,<4.0
Classifier: Programming Language :: Python :: 3
Classifier: Programming Language :: Python :: 3.11
Requires-Dist: fastapi (>=0,<1)
